pyarallel/__init__.py
pyarallel/config.py
pyarallel/config_manager.py
pyarallel/core.py
pyarallel/env_config.py
pyarallel-0.1.3.dist-info/METADATA
pyarallel-0.1.3.dist-info/WHEEL
pyarallel-0.1.3.dist-info/licenses/LICENSE.md
pyarallel-0.1.3.dist-info/RECORD
