Metadata-Version: 2.4
Name: pyarallel
Version: 0.1.3
Summary: A powerful parallel execution library for Python
Project-URL: Homepage, https://github.com/oneryalcin/pyarallel
Project-URL: Repository, https://github.com/oneryalcin/pyarallel.git
Project-URL: Documentation, https://github.com/oneryalcin/pyarallel
Author-email: Mehmet Oner Yalcin <oneryalcin@gmail.com>
License: MIT License
License-File: LICENSE.md
Classifier: Development Status :: 4 - Beta
Classifier: Intended Audience :: Developers
Classifier: License :: OSI Approved :: MIT License
Classifier: Programming Language :: Python :: 3
Classifier: Programming Language :: Python :: 3.12
Classifier: Topic :: Software Development :: Libraries :: Python Modules
Requires-Python: >=3.12
